{"data":[{"name":"IMG_0592.JPG","latitude":"51.473008","longitude":"-2.575278"},{"name":"IMG_0671.JPG","latitude":"51.441925","longitude":"-2.861564"},{"name":"IMG_0690.JPG","latitude":"51.441831","longitude":"-2.862267"},{"name":"IMG_0696.JPG","latitude":"51.435250","longitude":"-2.868500"},{"name":"IMG_0769.JPG","latitude":"51.469569","longitude":"-2.564536"},{"name":"IMG_0486.JPG","latitude":"51.466733","longitude":"-2.559000"},{"name":"IMG_0504.JPG","latitude":"51.467839","longitude":"-2.564567"},{"name":"IMG_0500.JPG","latitude":"51.467792","longitude":"-2.564736"},{"name":"IMG_0770.JPG","latitude":"51.469508","longitude":"-2.564506"},{"name":"IMG_0776.JPG","latitude":"51.469683","longitude":"-2.557764"},{"name":"IMG_0775.JPG","latitude":"51.469683","longitude":"-2.557764"},{"name":"IMG_0480.JPG","latitude":"51.466744","longitude":"-2.558842"},{"name":"IMG_0485.JPG","latitude":"51.466733","longitude":"-2.559000"},{"name":"IMG_0695.JPG","latitude":"51.435775","longitude":"-2.867722"},{"name":"IMG_0442.JPG","latitude":"51.485489","longitude":"-2.561011"},{"name":"IMG_0444.JPG","latitude":"51.486389","longitude":"-2.559475"},{"name":"IMG_0448.JPG","latitude":"51.489789","longitude":"-2.551611"},{"name":"IMG_0473.JPG","latitude":"51.469258","longitude":"-2.560219"},{"name":"IMG_0484.JPG","latitude":"51.466728","longitude":"-2.559014"},{"name":"IMG_0497.JPG","latitude":"51.467456","longitude":"-2.564558"},{"name":"IMG_0499.JPG","latitude":"51.467767","longitude":"-2.564533"},{"name":"IMG_0683.JPG","latitude":"51.441822","longitude":"-2.862247"},{"name":"IMG_0731.JPG","latitude":"51.456272","longitude":"-2.535228"},{"name":"IMG_0739.JPG","latitude":"51.468778","longitude":"-2.575386"},{"name":"IMG_0741.JPG","latitude":"51.468911","longitude":"-2.572831"},{"name":"IMG_0748.JPG","latitude":"51.467994","longitude":"-2.563603"},{"name":"IMG_0743.JPG","latitude":"51.468922","longitude":"-2.572797"},{"name":"IMG_0452.JPG","latitude":"51.489442","longitude":"-2.550664"},{"name":"IMG_0483.JPG","latitude":"51.466719","longitude":"-2.559003"},{"name":"IMG_0493.JPG","latitude":"51.466836","longitude":"-2.561431"},{"name":"IMG_0603.JPG","latitude":"51.477314","longitude":"-2.549828"},{"name":"IMG_0654.JPG","latitude":"51.473033","longitude":"-2.575175"},{"name":"IMG_0712.JPG","latitude":"51.463833","longitude":"-2.557475"},{"name":"IMG_0678.JPG","latitude":"51.441819","longitude":"-2.862242"},{"name":"IMG_0725.JPG","latitude":"51.455344","longitude":"-2.533081"},{"name":"IMG_0713.JPG","latitude":"51.463811","longitude":"-2.557625"},{"name":"IMG_0477.JPG","latitude":"51.466767","longitude":"-2.558739"},{"name":"IMG_0478.JPG","latitude":"51.466769","longitude":"-2.558836"},{"name":"IMG_0492.JPG","latitude":"51.466861","longitude":"-2.561400"},{"name":"IMG_0650.JPG","latitude":"51.469433","longitude":"-2.564364"},{"name":"IMG_0476.JPG","latitude":"51.466703","longitude":"-2.558461"},{"name":"IMG_0481.JPG","latitude":"51.466653","longitude":"-2.558867"},{"name":"IMG_0600.JPG","latitude":"51.477264","longitude":"-2.549883"},{"name":"IMG_0746.JPG","latitude":"51.468067","longitude":"-2.567606"},{"name":"IMG_0745.JPG","latitude":"51.468119","longitude":"-2.567606"},{"name":"IMG_0475.JPG","latitude":"51.466736","longitude":"-2.558581"},{"name":"IMG_0747.JPG","latitude":"51.467986","longitude":"-2.567597"},{"name":"IMG_0474.JPG","latitude":"51.469064","longitude":"-2.560192"},{"name":"IMG_0599.JPG","latitude":"51.477264","longitude":"-2.549883"},{"name":"IMG_0495.JPG","latitude":"51.466747","longitude":"-2.561542"},{"name":"IMG_0506.JPG","latitude":"51.468006","longitude":"-2.563633"},{"name":"IMG_0496.JPG","latitude":"51.466647","longitude":"-2.562214"},{"name":"IMG_0651.JPG","latitude":"51.472258","longitude":"-2.575264"},{"name":"IMG_0425.JPG","latitude":"51.469353","longitude":"-2.556731"},{"name":"IMG_0488.JPG","latitude":"51.466561","longitude":"-2.559731"},{"name":"IMG_0489.JPG","latitude":"51.466592","longitude":"-2.559792"},{"name":"IMG_0437.JPG","latitude":"51.481244","longitude":"-2.570406"},{"name":"IMG_0429.JPG","latitude":"51.470561","longitude":"-2.553706"},{"name":"IMG_0424.JPG","latitude":"51.469353","longitude":"-2.556731"}]}